cidex/py.typed
cidex/v2_1.py
cidex-0.1.1.dist-info/METADATA
cidex-0.1.1.dist-info/WHEEL
cidex-0.1.1.dist-info/top_level.txt
cidex-0.1.1.dist-info/RECORD
