Metadata-Version: 2.2
Name: cidex
Version: 0.1.1
Summary: the cidex manual/doc indexing specification
Requires-Python: >=3.11
Requires-Dist: aiohttp>=3.11.13
Requires-Dist: msgspec>=0.19.0
